MANIFEST.in
setup.py
./__init__.py
./__openerp__.py
i18n/ar.po
i18n/bg.po
i18n/bn.po
i18n/bs.po
i18n/ca.po
i18n/cs.po
i18n/da.po
i18n/de.po
i18n/en_AU.po
i18n/en_GB.po
i18n/es.po
i18n/es_CL.po
i18n/es_CR.po
i18n/es_DO.po
i18n/es_EC.po
i18n/es_MX.po
i18n/et.po
i18n/fa.po
i18n/fi.po
i18n/fr.po
i18n/gl.po
i18n/gu.po
i18n/he.po
i18n/hr.po
i18n/hu.po
i18n/it.po
i18n/ja.po
i18n/ka.po
i18n/ko.po
i18n/lo.po
i18n/lt.po
i18n/mk.po
i18n/mn.po
i18n/nb.po
i18n/nl.po
i18n/nl_BE.po
i18n/pl.po
i18n/pt.po
i18n/pt_BR.po
i18n/ro.po
i18n/ru.po
i18n/sl.po
i18n/sq.po
i18n/sr@latin.po
i18n/sv.po
i18n/th.po
i18n/tr.po
i18n/web_gantt.pot
i18n/zh_CN.po
openerp_web_gantt.egg-info/PKG-INFO
openerp_web_gantt.egg-info/SOURCES.txt
openerp_web_gantt.egg-info/dependency_links.txt
openerp_web_gantt.egg-info/requires.txt
openerp_web_gantt.egg-info/top_level.txt
static/lib/dhtmlxGantt/index.html
static/lib/dhtmlxGantt/codebase/dhtmlxcommon.js
static/lib/dhtmlxGantt/codebase/dhtmlxgantt.js
static/lib/dhtmlxGantt/codebase/imgs/arr.gif
static/lib/dhtmlxGantt/codebase/imgs/bg.png
static/lib/dhtmlxGantt/codebase/imgs/bg_week.png
static/lib/dhtmlxGantt/codebase/imgs/minus.gif
static/lib/dhtmlxGantt/codebase/imgs/parentnode_filled.png
static/lib/dhtmlxGantt/codebase/imgs/plus.gif
static/lib/dhtmlxGantt/codebase/imgs/progress_bg.png
static/lib/dhtmlxGantt/codebase/imgs/progress_filled.png
static/lib/dhtmlxGantt/codebase/imgs/menu/menu_bg.png
static/lib/dhtmlxGantt/codebase/imgs/menu/menu_selection.png
static/lib/dhtmlxGantt/codebase/imgs/menu/window_tr.png
static/lib/dhtmlxGantt/sources/dhtmlxcommon.js
static/lib/dhtmlxGantt/sources/dhtmlxgantt.js
static/src/js/gantt.js
static/src/xml/web_gantt.xml